cockpit/__init__.py
cockpit/cockpit.py
cockpit/context.py
cockpit/plotter.py
cockpit/instruments/__init__.py
cockpit/instruments/alpha_gauge.py
cockpit/instruments/cabs_gauge.py
cockpit/instruments/distance_gauge.py
cockpit/instruments/early_stopping_gauge.py
cockpit/instruments/grad_norm_gauge.py
cockpit/instruments/gradient_tests_gauge.py
cockpit/instruments/histogram_1d_gauge.py
cockpit/instruments/histogram_2d_gauge.py
cockpit/instruments/hyperparameter_gauge.py
cockpit/instruments/max_ev_gauge.py
cockpit/instruments/mean_gsnr_gauge.py
cockpit/instruments/performance_gauge.py
cockpit/instruments/tic_gauge.py
cockpit/instruments/trace_gauge.py
cockpit/instruments/utils_instruments.py
cockpit/instruments/utils_plotting.py
cockpit/quantities/__init__.py
cockpit/quantities/alpha.py
cockpit/quantities/bin_adaptation.py
cockpit/quantities/cabs.py
cockpit/quantities/distance.py
cockpit/quantities/early_stopping.py
cockpit/quantities/grad_hist.py
cockpit/quantities/grad_norm.py
cockpit/quantities/hess_max_ev.py
cockpit/quantities/hess_trace.py
cockpit/quantities/inner_test.py
cockpit/quantities/loss.py
cockpit/quantities/mean_gsnr.py
cockpit/quantities/norm_test.py
cockpit/quantities/ortho_test.py
cockpit/quantities/parameters.py
cockpit/quantities/quantity.py
cockpit/quantities/tic.py
cockpit/quantities/time.py
cockpit/quantities/update_size.py
cockpit/quantities/utils_hists.py
cockpit/quantities/utils_quantities.py
cockpit/quantities/utils_transforms.py
cockpit/quantities/hooks/__init__.py
cockpit/quantities/hooks/base.py
cockpit/quantities/hooks/cleanup.py
cockpit/utils/__init__.py
cockpit/utils/configuration.py
cockpit/utils/optim.py
cockpit/utils/schedules.py
cockpit_for_pytorch-1.0.2.dist-info/AUTHORS.md
cockpit_for_pytorch-1.0.2.dist-info/LICENSE.txt
cockpit_for_pytorch-1.0.2.dist-info/METADATA
cockpit_for_pytorch-1.0.2.dist-info/WHEEL
cockpit_for_pytorch-1.0.2.dist-info/top_level.txt
cockpit_for_pytorch-1.0.2.dist-info/RECORD
