Metadata-Version: 2.1
Name: cockpit-for-pytorch
Version: 1.0.2
Summary: A Practical Debugging Tool for Training Deep Neural Networks.
Home-page: https://github.com/f-dangel/cockpit
Author: Frank Schneider and Felix Dangel
Author-email: f.schneider@uni-tuebingen.de
License: MIT
Keywords: deep-learning,machine-learning,debugging
Platform: any
Classifier: Development Status :: 4 - Beta
Classifier: License :: OSI Approved :: MIT License
Classifier: Operating System :: OS Independent
Classifier: Programming Language :: Python :: 3.7
Classifier: Programming Language :: Python :: 3.8
Classifier: Programming Language :: Python :: 3.9
Requires-Python: >=3.7
License-File: LICENSE.txt
License-File: AUTHORS.md
Requires-Dist: json-tricks
Requires-Dist: matplotlib (>=3.4.0)
Requires-Dist: numpy
Requires-Dist: pandas
Requires-Dist: scipy
Requires-Dist: seaborn
Requires-Dist: torch
Requires-Dist: backpack-for-pytorch (>=1.3.0)
